MANIFEST.in
README.rst
buildout.cfg
develop.cfg
requirements.txt
setup.py
version.txt
bob/__init__.py
bob.db.gbu.egg-info/PKG-INFO
bob.db.gbu.egg-info/SOURCES.txt
bob.db.gbu.egg-info/dependency_links.txt
bob.db.gbu.egg-info/entry_points.txt
bob.db.gbu.egg-info/not-zip-safe
bob.db.gbu.egg-info/requires.txt
bob.db.gbu.egg-info/top_level.txt
bob/db/__init__.py
bob/db/gbu/__init__.py
bob/db/gbu/create.py
bob/db/gbu/driver.py
bob/db/gbu/models.py
bob/db/gbu/query.py
bob/db/gbu/test.py
bob/db/gbu/xmls.tar.gz
doc/conf.py
doc/guide.rst
doc/index.rst
doc/py_api.rst